{
  "title": "404 - الصفحة غير موجودة | Çorbacı",
  "description": "الصفحة التي تبحث عنها غير موجودة. يرجى العودة إلى الصفحة الرئيسية.",
  "keywords": "صفحة غير موجودة, 404",
  "partials": ["article-header", "parts", "article-footer"],
  "parts": [
    {
      "title": "الصفحة غير موجودة",
      "content": [
        "الصفحة التي تبحث عنها غير موجودة أو ربما تم نقلها.",
        "ربما جئت جائعاً وتحاول إيجاد القائمة؟"
      ],
      "list": [
        "العودة إلى الصفحة الرئيسية",
        "تصفح قائمتنا",
        "تواصل معنا"
      ]
    }
  ]
}
